wisecon/__init__.py
wisecon/agent/__init__.py
wisecon/agent/completions.py
wisecon/agent/tools/__init__.py
wisecon/agent/tools/register.py
wisecon/agent/tools/tools.py
wisecon/backtrader/evaluate/__init__.py
wisecon/backtrader/evaluate/base.py
wisecon/backtrader/evaluate/rolling.py
wisecon/car/__init__.py
wisecon/car/car_brand.py
wisecon/car/car_history_sales.py
wisecon/car/current_sales.py
wisecon/db/__init__.py
wisecon/db/duckdb.py
wisecon/feature/__init__.py
wisecon/feature/adjust.py
wisecon/feature/alpha101.py
wisecon/feature/operator.py
wisecon/fund/__init__.py
wisecon/fund/agent.py
wisecon/fund/base.py
wisecon/fund/fund_base.py
wisecon/fund/fund_company.py
wisecon/fund/fund_hist.py
wisecon/fund/fund_list.py
wisecon/fund/fund_rant.py
wisecon/fund/fund_trend.py
wisecon/fund/fund_value.py
wisecon/fund/search.py
wisecon/macro/__init__.py
wisecon/macro/asset_invest.py
wisecon/macro/base.py
wisecon/macro/boom_index.py
wisecon/macro/cpi.py
wisecon/macro/currency_supply.py
wisecon/macro/customs.py
wisecon/macro/deposit_rate.py
wisecon/macro/deposit_reserve.py
wisecon/macro/faith_index.py
wisecon/macro/fdi.py
wisecon/macro/forex_deposit.py
wisecon/macro/forex_loan.py
wisecon/macro/gdp.py
wisecon/macro/gold_currency.py
wisecon/macro/goodes_index.py
wisecon/macro/gov_income.py
wisecon/macro/hose_index.py
wisecon/macro/imp_intrestraten.py
wisecon/macro/index.py
wisecon/macro/indus_grow.py
wisecon/macro/lpr.py
wisecon/macro/new_loan.py
wisecon/macro/oil_price.py
wisecon/macro/pmi.py
wisecon/macro/ppi.py
wisecon/macro/stock_open.py
wisecon/macro/stock_statistics.py
wisecon/macro/tax.py
wisecon/macro/total_retail.py
wisecon/macro/transfer_fund.py
wisecon/mcp/__init__.py
wisecon/mcp/report.py
wisecon/mcp/stock.py
wisecon/mcp/stock_analysis.py
wisecon/mcp/validate.py
wisecon/movie/__init__.py
wisecon/movie/movie.py
wisecon/movie/tv.py
wisecon/parse/__init__.py
wisecon/parse/parse.py
wisecon/parse/parse_dict.py
wisecon/parse/parse_list.py
wisecon/report/__init__.py
iflow_mcp_wisecon-0.1.10.dist-info/METADATA
iflow_mcp_wisecon-0.1.10.dist-info/WHEEL
iflow_mcp_wisecon-0.1.10.dist-info/entry_points.txt
iflow_mcp_wisecon-0.1.10.dist-info/licenses/LICENSE
iflow_mcp_wisecon-0.1.10.dist-info/RECORD
