Metadata-Version: 2.4
Name: iflow-mcp_wisecon
Version: 0.1.10
Summary: A quant Python package.
Author-email: chensy cao <chensy.cao@foxmail.com>
Maintainer-email: chensy cao <chensy.cao@foxmail.com>
License: MIT
License-File: LICENSE
Keywords: Financial,MCP,Quant
Classifier: License :: OSI Approved :: MIT License
Classifier: Operating System :: OS Independent
Classifier: Programming Language :: Python :: 3.9
Classifier: Programming Language :: Python :: 3.10
Classifier: Programming Language :: Python :: 3.11
Classifier: Topic :: Software Development :: Libraries
Classifier: Topic :: Software Development :: Libraries :: Python Modules
Requires-Python: >=3.10
Requires-Dist: black>=25.1.0
Requires-Dist: bs4>=0.0.2
Requires-Dist: click>=8.1.8
Requires-Dist: fastmcp>=2.2.6
Requires-Dist: lumix>=0.0.7
Requires-Dist: numpy>=1.26.0
Requires-Dist: openai>=1.77.0
Requires-Dist: pandas>=2.2.3
Requires-Dist: requests>=2.32.3
Requires-Dist: scrapy>=2.12.0
Requires-Dist: selenium>=4.32.0
Requires-Dist: statsmodels>=0.14.4
Requires-Dist: tabulate>=0.9.0
Requires-Dist: tqdm>=4.67.1
Requires-Dist: webdriver-manager>=4.0.2
Provides-Extra: mkdocs
Requires-Dist: mkdocs-git-authors-plugin>=0.9.0; extra == 'mkdocs'
Requires-Dist: mkdocs-git-committers-plugin-2>=2.4.1; extra == 'mkdocs'
Requires-Dist: mkdocs-git-revision-date-localized-plugin>=1.3.0; extra == 'mkdocs'
Requires-Dist: mkdocs-glightbox>=0.4.0; extra == 'mkdocs'
Requires-Dist: mkdocs-material>=9.5.42; extra == 'mkdocs'
Requires-Dist: mkdocs-minify-plugin>=0.8.0; extra == 'mkdocs'
Requires-Dist: mkdocs-rss-plugin>=1.15.0; extra == 'mkdocs'
Requires-Dist: mkdocstrings>=0.26.2; extra == 'mkdocs'
